yokr/__init__.py
yokr/create_tables.sql
yokr/yokr.py
yokr/test/__init__.py
yokr/test/client.py
yokr/test/manualtest.py
yokr/test/server.py
yokr-0.3.4.dist-info/LICENSE
yokr-0.3.4.dist-info/METADATA
yokr-0.3.4.dist-info/WHEEL
yokr-0.3.4.dist-info/top_level.txt
yokr-0.3.4.dist-info/RECORD
