Metadata-Version: 2.1
Name: yokr
Version: 0.3.4
Summary: A client for Yokaranda SaaS
Home-page: https://yokaranda.com
Author: Gadi Solotorevsky
Author-email: gadi.solotorevsky@yokaranda.com
License: BSD-3-Clause
Platform: UNKNOWN
Classifier: Programming Language :: Python :: 3.6
Classifier: Development Status :: 4 - Beta
Classifier: License :: OSI Approved :: BSD License
Classifier: Operating System :: OS Independent
Requires-Python: >=3.6
Requires-Dist: requests
